sourceforprint
