Metadata-Version: 1.1
Name: lichanghongpip
Version: 1.0.3
Summary: this is a test package return a number
Home-page: https://github.com/lichanghong/wenyali.git
Author: wenyali
Author-email: 2917073217@qq.com
License: UNKNOWN
Keywords: number
Platform: UNKNOWN
Classifier: License :: OSI Approved :: MIT License
Classifier: Programming Language :: Python
Classifier: Intended Audience :: Developers
Classifier: Operating System :: OS Independent
